README.rst
setup.cfg
setup.py
dvc_objects/__init__.py
dvc_objects/_tqdm.py
dvc_objects/compat.py
dvc_objects/db.py
dvc_objects/errors.py
dvc_objects/executors.py
dvc_objects/obj.py
dvc_objects/py.typed
dvc_objects/transfer.py
dvc_objects_hdfs38.egg-info/PKG-INFO
dvc_objects_hdfs38.egg-info/SOURCES.txt
dvc_objects_hdfs38.egg-info/dependency_links.txt
dvc_objects_hdfs38.egg-info/requires.txt
dvc_objects_hdfs38.egg-info/top_level.txt