Metadata-Version: 2.1
Name: dvc_objects_hdfs38
Version: 3.0.7
Summary: original dvc-objects_3.0.6 with hdfs support tqdm (github.com/iterative/dvc/issues/8642) - filesystem and object-db level abstractions to use in dvc and dvc-data
Author: Ivan Tyurin
Author-email: 3464mustang+test_pypi@gmail.com
License: Apache-2.0
Project-URL: Issues, https://github.com/TyurinIvan/dvc-objects/issues
Project-URL: Source, https://github.com/TyurinIvan/dvc-objects
Classifier: Programming Language :: Python :: 3
Classifier: Programming Language :: Python :: 3.8
Classifier: License :: OSI Approved :: Apache Software License
Classifier: Operating System :: OS Independent
Requires-Python: >=3.8
Requires-Dist: fsspec
Requires-Dist: funcy
